askcsv/__init__.py
askcsv/analyzer.py
askcsv/cli.py
askcsv/webapp.py
askcsv/core/__init__.py
askcsv/core/charts.py
askcsv/core/executor.py
askcsv/core/plan.py
askcsv/core/profiling.py
askcsv/llm/__init__.py
askcsv/llm/gemini.py
askcsv/static/app.js
askcsv/static/index.html
askcsv/static/styles.css
askcsv/static/assets/askcsv-logo-horizontal.png
askcsv/static/assets/askcsv-logo-mark.png
askcsv/static/assets/favicon.png
askcsv-0.1.2.dist-info/METADATA
askcsv-0.1.2.dist-info/WHEEL
askcsv-0.1.2.dist-info/entry_points.txt
askcsv-0.1.2.dist-info/licenses/LICENSE
askcsv-0.1.2.dist-info/RECORD
