Metadata-Version: 2.4
Name: askcsv
Version: 0.1.2
Summary: Ask questions to your CSV in a local web chat UI using Gemini.
Author: Nirajan Ghimire
License: MIT
License-File: LICENSE
Requires-Python: >=3.9
Requires-Dist: fastapi>=0.110.0
Requires-Dist: matplotlib>=3.7.0
Requires-Dist: pandas>=2.0.0
Requires-Dist: uvicorn>=0.27.0
Provides-Extra: gemini
Requires-Dist: google-genai>=0.3.0; extra == 'gemini'
